MANIFEST.in
README.md
requirements.txt
setup.py
Sukusho/__init__.py
Sukusho/daemonize.py
Sukusho/main.py
Sukusho/mv_screenshot.py
Sukusho/settings.py
Sukusho.egg-info/PKG-INFO
Sukusho.egg-info/SOURCES.txt
Sukusho.egg-info/dependency_links.txt
Sukusho.egg-info/entry_points.txt
Sukusho.egg-info/requires.txt
Sukusho.egg-info/top_level.txt