Metadata-Version: 2.1
Name: Sukusho
Version: 0.1.0
Summary: Easy screenshot sorter for Mac for students
Home-page: https://github.com/pn8128/scr_utils
Author: kota oishi
Author-email: oishi-kota454@g.ecc.u-tokyo.ac.jp
License: MIT
Platform: UNKNOWN
Classifier: Programming Language :: Python :: 3
Classifier: License :: OSI Approved :: MIT License
Classifier: Operating System :: OS Independent
Requires-Python: >=3.6
